Workbook

Sheet Peça Orçamentária - Analítica
A1: ESTUDO DE ORÇAMENTO 2025
A2: ITEM DE DESPESA | B2: 2025 - 10,5 % | C2: 2025 - 10,5 % | D2: RESULTADO | E2: PROPOSTA 2026
B3: ORÇADO | C3: REALIZADO | D3: 2024 | E3: 10,00 | F3: Contratação de:
A4: DESPESAS GERAIS COM PESSOAL | B4: =B6+B11+B16+B21+B24 -> 1561450 | C4: =C6+C11+C16+C21+C24 -> 1187825.1 | D4: =B4-C4 -> 373624.88 | E4: =E6+E11+E16+E21+E24 -> 1958500 | F4: 01 Supervisor de Segurança
A5: DA ADM / MANUTENÇÃO | F5: 01 Auxiliar Administrativa
A6: TOTAL SALÁRIOS E ENCARGOS | B6: =SUM(B7:B10) -> 961800 | C6: =SUM(C7:C10) -> 839206.34 | D6: =SUM(D7:D10) -> 122593.66 | E6: =SUM(E7:E10) -> 1149000 | F6: 01 Faxineira
A7: Salários / Adicionais / Horas Extras | B7: 710000 | C7: 608756.22 | D7: =B7-C7 -> 101243.78 | E7: 850000
A8: INSS - 25,5% | B8: 182000 | C8: 170223.99 | D8: =B8-C8 -> 11776.01 | E8: 220000
A9: FGTS - 8% | B9: 61000 | C9: 53559.5 | D9: =B9-C9 -> 7440.5 | E9: 70000
A10: PIS - 1% | B10: 8800 | C10: 6666.63 | D10: =B10-C10 -> 2133.37 | E10: 9000
A11: TOTAL FÉRIAS E ENCARGOS | B11: =SUM(B12:B15) -> 126440 | C11: =SUM(C12:C15) -> 100491.61 | D11: =SUM(D12:D15) -> 33581.67 | E11: =SUM(E12:E15) -> 130000
A12: Férias - 33,33% | B12: 94000 | C12: 76198.4 | D12: =B12-C12 -> 17801.6 | E12: 95000
A13: INSS - 25,5% | B13: 24000 | C13: 17955.87 | D13: =B13-C13 -> 6044.13 | E13: 25000
A14: FGTS - 8% | B14: 7500 | C14: 5633.28 | D14: 9500 | E14: 8500
A15: PIS - 1% | B15: 940 | C15: 704.06 | D15: =B15-C15 -> 235.94 | E15: 1500
A16: TOTAL 13.º SALÁRIO E ENCARGOS | B16: =SUM(B17:B20) -> 83880 | C16: =SUM(C17:C20) -> 72693.47 | D16: =SUM(D17:D20) -> 11186.53 | E16: =SUM(E17:E20) -> 103500
A17: 13.º Salário | B17: 61000 | C17: 54422.33 | D17: =B17-C17 -> 6577.67 | E17: 75000
A18: INSS - 25,5% | B18: 16500 | C18: 13504.79 | D18: =B18-C18 -> 2995.21 | E18: 20000
A19: FGTS - 8% | B19: 5500 | C19: 4236.84 | D19: =B19-C19 -> 1263.16 | E19: 7000
A20: PIS - 1% | B20: 880 | C20: 529.51 | D20: =B20-C20 -> 350.49 | E20: 1500
A21: PROVISÕES TRABALHISTAS | B21: =B22+B23 -> 19250 | C21: =C22+C23 -> 0 | D21: =D22+D23 -> 19250 | E21: =E22+E23 -> 102500
A22: Provisões Ações Trabalhistas | B22: 17600 | D22: =B22-C22 -> 17600 | E22: 100000
A23: Exames Médicos | B23: 1650 | D23: =B23-C23 -> 1650 | E23: 2500
A24: BENEFÍCIOS | B24: =SUM(B25:B33) -> 370080 | C24: =SUM(C25:C33) -> 175433.7 | D24: =SUM(D25:D33) -> 194646.3 | E24: =SUM(E25:E33) -> 473500
A25: Vale Transporte | B25: 12000 | C25: 8923.74 | D25: =B25-C25 -> 3076.26 | E25: 16000
A26: Vale Cesta | B26: 63500 | D26: =B26-C26 -> 63500 | E26: 80000
A27: Vale Refeição | B27: 76000 | D27: =B27-C27 -> 76000 | E27: 92000
A28: Cesta de Natal / VR Natal | B28: 25500 | D28: =B28-C28 -> 25500 | E28: 26000
A29: Assistencia Médica / Odontológica | B29: 155000 | C29: 144858.27 | D29: =B29-C29 -> 10141.73 | E29: 210000
A30: Seguro de Vida | B30: 2880 | C30: 3240 | D30: =B30-C30 -> -360 | E30: 1500
A31: Treinamentos/Cursos/Bolsa Educação | B31: 7000 | C31: 7375.02 | D31: =B31-C31 -> -375.02 | E31: 12000
A32: Uniformes | B32: 14100 | C32: 11036.67 | D32: =B32-C32 -> 3063.33 | E32: 18000
A33: Equipamentos de Proteção Individual | B33: 14100 | D33: =B33-C33 -> 14100 | E33: 18000
A34: OUTRAS DESPESAS ADMINISTRATIVAS | B34: =SUM(B35:B58) -> 264040 | C34: =SUM(C35:C58) -> 173660.77 | D34: =SUM(D35:D58) -> 79558.23 | E34: =SUM(E35:E58) -> 274200
A35: Cartórios e Emolumentos | B35: 4500 | C35: 1077.83 | D35: =B35-C35 -> 3422.17 | E35: 5000
A36: Seguro Patrimonial | B36: 6000 | C36: 4735.66 | D36: =B36-C36 -> 1264.34 | E36: 6500
A37: Publicação (Edital) | B37: 1800 | C37: 362 | D37: =B37-C37 -> 1438 | E37: 2500
A38: Material de Escritório | B38: 5900 | C38: 6158.29 | D38: =B38-C38 -> -258.29 | E38: 7000
A39: Material Copa e Cozinha | B39: 29500 | C39: 30419.17 | D39: =B39-C39 -> -919.17 | E39: 33000
A40: Despesas com Reuniões / AGO / AGE | B40: 11000 | D40: =B40-C40 -> 11000 | E40: 12000
A41: Despesas com Sindicatos | B41: 1180 | D41: =B41-C41 -> 1180 | E41: 1500
A42: Conduções/Motoboy | B42: 1760 | D42: =B42-C42 -> 1760 | E42: 1800
A43: Material de Informática | B43: 9400 | D43: =B43-C43 -> 9400 | E43: 20000
A44: Provedor | B44: 2950 | C44: 289.9 | D44: =B44-C44 -> 2660.1 | E44: 3500
A45: Faixas/Banners | B45: 4120 | C45: 2845.33 | D45: =B45-C45 -> 1274.67 | E45: 5000
A46: Material Limpeza e Higiene | B46: 29300 | C46: 18837.26 | D46: =B46-C46 -> 10462.74 | E46: 32000
A47: PPRA/PCMSO/LTCAT | B47: 2950 | C47: 1500 | D47: =B47-C47 -> 1450 | E47: 3500
A48: Estacionamentos / Pedágios | B48: 6600 | C48: 8201.26 | D48: =B48-C48 -> -1601.26 | E48: 7500
A49: Agua e Esgoto | B49: 53000 | C49: 49157.07 | D49: =B49-C49 -> 3842.93 | E49: 53000
A50: Telefonia - Fixa e Celular - PABX | B50: 29300 | C50: 24958.05 | D50: =B50-C50 -> 4341.95 | E50: 25000
A51: Energia Eletrica | B51: 30000 | D51: 19179 | E51: 25000
A52: Despesas de Postagens | B52: 2350 | C52: 55.65 | D52: =B52-C52 -> 2294.35 | E52: 3500
A53: Lavanderia | B53: 1100 | D53: =B53-C53 -> 1100 | E53: 1500
A54: Chaveiro | B54: 550 | D54: =B54-C54 -> 550 | E54: 600
A55: Taxas e Licenças | B55: 5500 | D55: =B55-C55 -> 5500 | E55: 6500
A56: Despesas Processuais | B56: 17600 | C56: 23752.08 | D56: =B56-C56 -> -6152.08 | E56: 5000
A57: Materiais de Primeiros Socorros / Medicação | B57: 1180 | C57: 1311.22 | D57: =B57-C57 -> -131.22 | E57: 1300
A58: Locação de Equipamentos AGO / AGE - Painel LED | B58: 6500 | D58: =B58-C58 -> 6500 | E58: 12000
A59: SERVIÇOS DE TERCEIROS | B59: =SUM(B60:B72) -> 285400 | C59: =SUM(C60:C72) -> 195771.79 | D59: =SUM(D60:D72) -> 89628.21 | E59: =SUM(E60:E72) -> 290300
A60: Serviços Contratados - Contabilidade | B60: 45000 | C60: 40740 | D60: =B60-C60 -> 4260 | E60: 45000
A61: Serviços Contratados - Advocacia | B61: 35000 | C61: 32543.28 | D61: =B61-C61 -> 2456.72 | E61: 35000
A62: Serviços Contratados - Auditoria | B62: 16000 | C62: 9600 | D62: =B62-C62 -> 6400 | E62: 15000
A63: Serviços Contratados - Despesas com Xerox (Contrato) | B63: 18000 | C63: 6252.68 | D63: =B63-C63 -> 11747.32 | E63: 18000
A64: Serviços Contratados - Relógio de Ponto | B64: 3400 | C64: 1996.92 | D64: =B64-C64 -> 1403.08 | E64: 3400
A65: Serviços Contratados - Análise de Projetos | B65: 41000 | C65: 36372 | D65: =B65-C65 -> 4628 | E65: 43000
A66: Serviços Contratados - Assessoria de Rede (Colla) | B66: 34000 | C66: 22692.5 | D66: =B66-C66 -> 11307.5 | E66: 34000
A67: Serviços Cont. - Cont. de Acessos - BELSI | B67: 37000 | C67: 7416 | D67: =B67-C67 -> 29584 | E67: 39000
A68: Serviços Cont. - Consultas - BIOACESSO | B68: 6400 | D68: =B68-C68 -> 6400 | E68: 6400
A69: Contrato de Manutenção de Cancelas - Grupo SIS | B69: 16200 | C69: 26509.41 | D69: =B69-C69 -> -10309.41 | E69: 16000
A70: Serviços Contratados - Sistema Financeiro - Marin | B70: 20300 | C70: 11649 | D70: =B70-C70 -> 8651 | E70: 22000
A71: Serviços Contratados - Manutenção Usina Fotovoltaica | B71: 4800 | D71: =B71-C71 -> 4800 | E71: 5000
A72: Serviços Contratados - Manutenção ar condicionado | B72: 8300 | D72: =B72-C72 -> 8300 | E72: 8500
A73: MANUTENÇÃO AREAS COMUNS | B73: =SUM(B74:B85) -> 1079700 | C73: =SUM(C74:C85) -> 1026244.3 | D73: =SUM(D74:D85) -> 53455.71 | E73: =SUM(E74:E85) -> 1191000
A74: Contrato de Jardinagem - J. Vieira | B74: 800000 | C74: 894994.67 | D74: =B74-C74 -> -94994.67 | E74: 825000
A75: Manutenção do Jardim | B75: 23500 | D75: =B75-C75 -> 23500 | E75: 35000
A76: Manutenção Geral - Portaria / Adm / Serviços | B76: 90000 | C76: 109459.99 | D76: =B76-C76 -> -19459.99 | E76: 150000
A77: Manutenção Quadra Poliesportiva | B77: 25000 | C77: 769 | D77: =B77-C77 -> 24231 | E77: 25000
A78: Manutenção Quadra de Tenis | B78: 35400 | C78: 355 | D78: =B78-C78 -> 35045 | E78: 35000
A79: Manutenção dos Parques | B79: 27500 | D79: =B79-C79 -> 27500 | E79: 30000
A80: Manutenção Salão Multiuso | B80: 25000 | D80: =B80-C80 -> 25000 | E80: 25000
A81: Manutenção Academia ao ar Livre e Bicicross | B81: 5900 | D81: =B81-C81 -> 5900 | E81: 6500
A82: Manutenção Gerador | B82: 5900 | D82: =B82-C82 -> 5900 | E82: 6500
A83: Manutenção Maqs/Móveis/Equipamentos | B83: 11750 | C83: 11756.84 | D83: =B83-C83 -> -6.84 | E83: 13000
A84: Manutenção Elétrica / Hidráulica | B84: 11750 | D84: =B84-C84 -> 11750 | E84: 15000
A85: Manutenção de Vias Publicas | B85: 18000 | C85: 8908.79 | D85: =B85-C85 -> 9091.21 | E85: 25000
A86: Manutenção de áreas públicas - Dedetização | B86: 11000 | D86: =B86-C86 -> 11000 | E86: 13000
A87: SEGURANÇA | B87: =SUM(B88:B95) -> 6191000 | C87: =SUM(C88:C95) -> 5222296.8 | D87: =SUM(D88:D95) -> 968703.2 | E87: =SUM(E88:E95) -> 5601200
A88: Serviços Contrat. de Vigilancia - PJ (Contrato) | B88: 4520000 | C88: 3786038.4 | D88: =B88-C88 -> 733961.58 | E88: 4000000
A89: Serviços Cooperados - SMAS | B89: 1010000 | C89: 861447.24 | D89: =B89-C89 -> 148552.76 | E89: 950000
A90: Equipamentos, Sinalizadores de Trânsito e Lombadas | B90: 11800 | D90: =B90-C90 -> 11800 | E90: 7000
A91: Locação Sistema Monitoramento e Cerca Elétrica - TV Alphaville | B91: 425000 | C91: 400604.8 | D91: =B91-C91 -> 24395.198 | E91: 456000
A92: Combustiveis e Lubrificantes - Segurança | B92: 96000 | C92: 75249.57 | D92: =B92-C92 -> 20750.43 | E92: 60000
A93: Materiais de Segurança | B93: 10000 | D93: =B93-C93 -> 10000 | E93: 10000
A94: Locação de Veículos | B94: 110000 | C94: 91959.81 | D94: =B94-C94 -> 18040.19 | E94: 110000
A95: Locação de Rádios | B95: 8200 | C95: 6996.96 | D95: =B95-C95 -> 1203.04 | E95: 8200
A96: DESPESAS COM VEÍCULOS | B96: =SUM(B97:B99) -> 21600 | C96: =SUM(C97:C99) -> 8145.96 | D96: =SUM(D97:D99) -> 13454.04 | E96: =SUM(E97:E99) -> 21600
A97: Manutenção de Veiculos | B97: 11800 | C97: 6056.74 | D97: =B97-C97 -> 5743.26 | E97: 11800
A98: IPVA/Licenc./Despachante | B98: 5800 | C98: 1067.42 | D98: =B98-C98 -> 4732.58 | E98: 5800
A99: Seguro de Veiculos | B99: 4000 | C99: 1021.8 | D99: =B99-C99 -> 2978.2 | E99: 4000
A100: EVENTOS SOCIAIS/ESPORTIVOS | B100: =SUM(B101:B111) -> 464700 | C100: =SUM(C101:C111) -> 170334.6 | D100: =SUM(D101:D111) -> 294365.4 | E100: =SUM(E101:E111) -> 484000
...

Sheet Peça Orçamentária - Sintética
A1: ESTUDO DE ORÇAMENTO 2026 | F1: PROPOSTA DE REDUÇÃO NAS DIRETORIAS
A2: ITEM DE DESPESA | B2: 2025 - 10,5 % | C2: 2025 - 10,5 % | D2: RESULTADO | E2: PROPOSTA 2026
B3: ORÇADO | C3: REALIZADO | D3: 2025 | E3: 10,00
A4: DESPESAS GERAIS COM PESSOAL - ADM / MANUTENÇÃO | B4: ='Peça Orçamentária - Analítica'!B4:B5 -> 1561450 | C4: ='Peça Orçamentária - Analítica'!C4:C5 -> 1187825.1 | D4: ='Peça Orçamentária - Analítica'!D4:D5 -> 373624.88 | E4: ='Peça Orçamentária - Analítica'!E4:E5 -> 1958500
A5: OUTRAS DESPESAS ADMINISTRATIVAS | B5: ='Peça Orçamentária - Analítica'!B34 -> 264040 | C5: ='Peça Orçamentária - Analítica'!C34 -> 173660.77 | D5: ='Peça Orçamentária - Analítica'!D34 -> 79558.23 | E5: ='Peça Orçamentária - Analítica'!E34 -> 274200 | F5: Dir Administrativa | G5: 0.04 | H5: =2008500*4% -> 80340
A6: SERVIÇOS DE TERCEIROS | B6: ='Peça Orçamentária - Analítica'!B59 -> 285400 | C6: ='Peça Orçamentária - Analítica'!C59 -> 195771.79 | D6: ='Peça Orçamentária - Analítica'!D59 -> 89628.21 | E6: ='Peça Orçamentária - Analítica'!E59 -> 290300 | F6: Dir Segurança | G6: 0.04 | H6: =5821200*4% -> 232848
A7: MANUTENÇÃO AREAS COMUNS | B7: ='Peça Orçamentária - Analítica'!B73 -> 1079700 | C7: ='Peça Orçamentária - Analítica'!C73 -> 1026244.3 | D7: ='Peça Orçamentária - Analítica'!D73 -> 53455.71 | E7: ='Peça Orçamentária - Analítica'!E73 -> 1191000 | F7: Dir Manut. Obras | G7: 0.1 | H7: =1206000*10% -> 120600
A8: SEGURANÇA | B8: ='Peça Orçamentária - Analítica'!B87 -> 6191000 | C8: ='Peça Orçamentária - Analítica'!C87 -> 5222296.8 | D8: ='Peça Orçamentária - Analítica'!D87 -> 968703.2 | E8: ='Peça Orçamentária - Analítica'!E87 -> 5601200 | F8: Dir Social | G8: 0.2 | H8: =401000*20% -> 80200
A9: DESPESAS COM VEÍCULOS | B9: ='Peça Orçamentária - Analítica'!B96 -> 21600 | C9: ='Peça Orçamentária - Analítica'!C96 -> 8145.96 | D9: ='Peça Orçamentária - Analítica'!D96 -> 13454.04 | E9: ='Peça Orçamentária - Analítica'!E96 -> 21600
A10: EVENTOS SOCIAIS/ESPORTIVOS | B10: ='Peça Orçamentária - Analítica'!B100 -> 464700 | C10: ='Peça Orçamentária - Analítica'!C100 -> 170334.6 | D10: ='Peça Orçamentária - Analítica'!D100 -> 294365.4 | E10: ='Peça Orçamentária - Analítica'!E100 -> 484000 | F10: TOTAL | H10: =SUM(H5:H9) -> 513988
A11: INVESTIMENTOS | B11: ='Peça Orçamentária - Analítica'!B113 -> 1118000 | C11: ='Peça Orçamentária - Analítica'!C113 -> 3791029.5 | D11: ='Peça Orçamentária - Analítica'!D113 -> -2673029.5 | E11: ='Peça Orçamentária - Analítica'!E113 -> 1803500
A12: IMPOSTOS TAXAS E CONTRIBUIÇÕES | B12: ='Peça Orçamentária - Analítica'!B122 -> 476500 | C12: ='Peça Orçamentária - Analítica'!C122 -> 499750.89 | D12: ='Peça Orçamentária - Analítica'!D122 -> -23250.89 | E12: ='Peça Orçamentária - Analítica'!E122 -> 560500
A13: DESPESAS FINANCEIRAS | B13: ='Peça Orçamentária - Analítica'!B128 -> 23520 | C13: ='Peça Orçamentária - Analítica'!C128 -> 29110.44 | D13: ='Peça Orçamentária - Analítica'!D128 -> -5590.44 | E13: ='Peça Orçamentária - Analítica'!E128 -> 19000
A14: TOTAL DESPESAS | B14: ='Peça Orçamentária - Analítica'!B132 -> 11485910 | C14: ='Peça Orçamentária - Analítica'!C132 -> 12304170 | D14: ='Peça Orçamentária - Analítica'!D132 -> -821447.86 | E14: ='Peça Orçamentária - Analítica'!E132 -> 12203800
A16: CONTAS - RECEITAS | B16: 2025 - 10,5 % | C16: 2025 - 10,5 % | D16: RESULTADO | E16: PROPOSTA 2026
B17: ORÇADO | C17: REALIZADO | D17: 2025 | E17: 10,00
A18: TAXA DE MANUTENÇÃO - FATURAMENTO | B18: ='Peça Orçamentária - Analítica'!B137 -> 11079955 | C18: ='Peça Orçamentária - Analítica'!C137 -> 10584462 | D18: ='Peça Orçamentária - Analítica'!D137 -> -495493.45 | E18: ='Peça Orçamentária - Analítica'!E137 -> 12187950
A19: RECEITAS FINANCEIRAS DIVERSAS | B19: ='Peça Orçamentária - Analítica'!B140 -> 327000 | C19: ='Peça Orçamentária - Analítica'!C140 -> 591779.95 | D19: ='Peça Orçamentária - Analítica'!D140 -> 264779.95 | E19: ='Peça Orçamentária - Analítica'!E140 -> 301700
A20: TOTAL GERAL DE RECEITAS | B20: ='Peça Orçamentária - Analítica'!B146 -> 11027387 | C20: ='Peça Orçamentária - Analítica'!C146 -> 10521816 | D20: ='Peça Orçamentária - Analítica'!D146 -> -505571.09 | E20: ='Peça Orçamentária - Analítica'!E146 -> 12220126
